mapactionpy_arcmap/__init__.py
mapactionpy_arcmap/arc_layer_dumper.py
mapactionpy_arcmap/arcmap_runner.py
mapactionpy_arcmap/map_chef.py
mapactionpy_arcmap/map_data.py
mapactionpy_arcmap/mapframe_builder.py
mapactionpy_arcmap/temp_lyrname_updater.py
mapactionpy_arcmap/tests/__init__.py
mapactionpy_arcmap/tests/fixtures.py
mapactionpy_arcmap/tests/test_map_chef.py
mapactionpy_arcmap/tests/test_mapactionpy_arcmap.py
mapactionpy_arcmap-0.10.1.dist-info/METADATA
mapactionpy_arcmap-0.10.1.dist-info/WHEEL
mapactionpy_arcmap-0.10.1.dist-info/top_level.txt
mapactionpy_arcmap-0.10.1.dist-info/RECORD
