Metadata-Version: 2.1
Name: mapactionpy-arcmap
Version: 0.10.1
Summary: Used to drive ArcMap
Home-page: http://github.com/mapaction/mapactionpy_arcmap
Author: MapAction
Author-email: github@mapaction.com
License: GPL3
Platform: UNKNOWN
Classifier: Development Status :: 2 - Pre-Alpha
Classifier: Programming Language :: Python :: 2.7
Classifier: License :: OSI Approved :: GNU General Public License v3 (GPLv3)
Classifier: Operating System :: Microsoft :: Windows
Requires-Dist: argparse
Requires-Dist: requests
Requires-Dist: pycountry
Requires-Dist: slugify
Requires-Dist: jsonpickle
Requires-Dist: Pillow
Requires-Dist: python-resize-image
